test/__init__.py
test/test_ansible_api.py
test/test_audit_api.py
test/test_command_api.py
test/test_file_api.py
test/test_health_api.py
test/test_human_api.py
test/test_internal_ansible_job.py
test/test_internal_ansible_job_request.py
test/test_internal_ansible_job_response.py
test/test_internal_ansible_job_status.py
test/test_internal_rest_create_sandbox_request.py
test/test_internal_rest_create_sandbox_response.py
test/test_internal_rest_diff_request.py
test/test_internal_rest_diff_response.py
test/test_internal_rest_error_response.py
test/test_internal_rest_generate_response.py
test/test_internal_rest_inject_ssh_key_request.py
test/test_internal_rest_list_vms_response.py
test/test_internal_rest_publish_request.py
test/test_internal_rest_publish_response.py
test/test_internal_rest_run_command_request.py
test/test_internal_rest_run_command_response.py
test/test_internal_rest_snapshot_request.py
test/test_internal_rest_snapshot_response.py
test/test_internal_rest_start_sandbox_request.py
test/test_internal_rest_start_sandbox_response.py
test/test_internal_rest_vm_info.py
test/test_plan_api.py
test/test_sandbox_api.py
test/test_time_duration.py
test/test_tmux_api.py
test/test_tmux_client_internal_types_api_error.py
test/test_tmux_client_internal_types_approval_status.py
test/test_tmux_client_internal_types_approve_request.py
test/test_tmux_client_internal_types_ask_human_request.py
test/test_tmux_client_internal_types_ask_human_response.py
test/test_tmux_client_internal_types_audit_entry.py
test/test_tmux_client_internal_types_audit_query.py
test/test_tmux_client_internal_types_audit_query_response.py
test/test_tmux_client_internal_types_component_health.py
test/test_tmux_client_internal_types_copy_file_request.py
test/test_tmux_client_internal_types_copy_file_response.py
test/test_tmux_client_internal_types_create_pane_request.py
test/test_tmux_client_internal_types_create_pane_response.py
test/test_tmux_client_internal_types_create_plan_request.py
virsh_sandbox-0.0.5b0.dist-info/METADATA
virsh_sandbox-0.0.5b0.dist-info/WHEEL
virsh_sandbox-0.0.5b0.dist-info/top_level.txt
virsh_sandbox-0.0.5b0.dist-info/RECORD
