Metadata-Version: 2.4
Name: virsh_sandbox
Version: 0.0.5b0
Summary: virsh-sandbox API
Home-page: https://github.com/aspectrr/virsh-sandbox
Author: Collin Pfeifer
Author-email: OpenAPI Generator Community <team@openapitools.org>
Project-URL: Repository, https://github.com/GIT_USER_ID/GIT_REPO_ID
Keywords: OpenAPI,OpenAPI-Generator,virsh-sandbox API
Requires-Python: >=3.8
Requires-Dist: urllib3<3.0.0,>=2.1.0
Requires-Dist: python-dateutil>=2.8.2
Requires-Dist: aiohttp>=3.8.4
Requires-Dist: aiohttp-retry>=2.8.3
Requires-Dist: pydantic>=2
Requires-Dist: typing-extensions>=4.7.1
Dynamic: author
Dynamic: home-page
Dynamic: requires-python
